flexlog/__init__.py
flexlog/cleanlogger.py
flexlog-1.5.0.dist-info/LICENSE
flexlog-1.5.0.dist-info/METADATA
flexlog-1.5.0.dist-info/WHEEL
flexlog-1.5.0.dist-info/top_level.txt
flexlog-1.5.0.dist-info/RECORD
