Metadata-Version: 2.1
Name: flexlog
Version: 1.5.0
Summary: A convenience package to add a flexible logger easily.
Home-page: https://gitlab.com/optano/flexlog
Author: Sven Flake
Author-email: sven.flake@optano.com
License: UNKNOWN
Platform: UNKNOWN
Classifier: Programming Language :: Python :: 3
Classifier: License :: OSI Approved :: MIT License
Classifier: Operating System :: OS Independent
Requires-Python: >=3.6
License-File: LICENSE
